README.md
setup.py
RunTeleBot/Funciones.py
RunTeleBot/__init__.py
RunTeleBot/db.py
RunTeleBot.egg-info/PKG-INFO
RunTeleBot.egg-info/SOURCES.txt
RunTeleBot.egg-info/dependency_links.txt
RunTeleBot.egg-info/requires.txt
RunTeleBot.egg-info/top_level.txt
RunTeleBot/ptbot/__init__.py
RunTeleBot/ptbot/commands.py
RunTeleBot/ptbot/main.py
RunTeleBot/pyrobot/__init__.py
RunTeleBot/pyrobot/callbackquerys.py
RunTeleBot/pyrobot/commands.py
RunTeleBot/pyrobot/main.py