Metadata-Version: 2.1
Name: RunTeleBot
Version: 0.1.2
Summary: Librería para ayudar a crear bots de Telegram.
Home-page: https://github.com/RaulCobiellas
Author: Raú Enrique Cobiellas Colomé
Author-email: raulcobiellas@gmail.com
License: MIT
Platform: UNKNOWN
